kgedata
kgekit
