Metadata-Version: 2.1
Name: kgekit
Version: 0.24.0
Summary: knowledge representation tools
Home-page: http://github.com/fantasticfears/kgekit
Author: Erick Guan
Author-email: fantasticfears@gmail.com
License: GPLv2
Platform: UNKNOWN
Classifier: Development Status :: 4 - Beta
Classifier: License :: OSI Approved :: GNU General Public License v2 (GPLv2)
Classifier: Intended Audience :: Developers
Classifier: Programming Language :: Python :: 3
